<PAMDataset>
  <PAMRasterBand band="1">
    <Histograms>
      <HistItem>
        <HistMin>-26.461437225342</HistMin>
        <HistMax>9.265330314636198</HistMax>
        <BucketCount>256</BucketCount>
        <IncludeOutOfRange>1</IncludeOutOfRange>
        <Approximate>0</Approximate>
        <HistCounts>1|0|0|0|0|1|0|2|1|1|3|1|1|2|6|11|6|11|8|11|10|14|10|18|17|16|13|23|28|27|21|32|29|29|36|52|46|60|58|50|52|65|83|91|75|76|109|94|106|111|118|125|145|140|174|175|189|191|221|222|257|278|297|344|346|324|403|457|450|514|536|566|602|680|666|714|794|864|833|861|899|965|984|1009|1159|1149|1177|1222|1291|1309|1320|1458|1510|1502|1545|1513|1589|1674|1736|1783|1819|2020|2040|2132|2161|2427|2418|2639|2787|2970|3102|3180|3266|3351|3463|3363|3419|3443|3265|3378|3252|3338|3213|3204|3078|3051|2893|2705|2601|2455|2222|2093|1877|1691|1530|1397|1170|1061|859|745|656|506|457|342|297|265|192|156|120|92|85|73|52|51|40|29|25|18|14|19|12|15|9|13|9|6|10|5|4|1|4|3|4|0|2|1|4|2|2|1|1|3|0|0|0|1|0|1|1|1|0|1|0|1|2|1|0|0|0|0|1|0|1|1|0|1|0|0|0|0|0|0|0|0|0|1|0|0|1|1|0|0|0|0|0|0|0|0|0|0|0|0|0|0|0|0|0|0|0|0|0|0|0|0|1|0|0|0|0|0|0|0|0|0|0|1</HistCounts>
      </HistItem>
    </Histograms>
    <Metadata>
      <MDI key="STATISTICS_COVARIANCES">8.187809131991502</MDI>
      <MDI key="STATISTICS_MAXIMUM">9.2653303146362</MDI>
      <MDI key="STATISTICS_MEAN">-11.17895697968</MDI>
      <MDI key="STATISTICS_MINIMUM">-26.461437225342</MDI>
      <MDI key="STATISTICS_SKIPFACTORX">1</MDI>
      <MDI key="STATISTICS_SKIPFACTORY">1</MDI>
      <MDI key="STATISTICS_STDDEV">2.86143480303</MDI>
    </Metadata>
  </PAMRasterBand>
</PAMDataset>
