<PAMDataset>
  <PAMRasterBand band="1">
    <Histograms>
      <HistItem>
        <HistMin>-32.475135803223</HistMin>
        <HistMax>-6.204359531402601</HistMax>
        <BucketCount>256</BucketCount>
        <IncludeOutOfRange>1</IncludeOutOfRange>
        <Approximate>0</Approximate>
        <HistCounts>1|0|0|0|0|0|0|0|0|0|1|0|1|0|1|0|1|0|0|1|0|0|0|1|1|0|1|0|0|0|0|0|0|3|0|1|1|0|1|2|1|0|0|3|1|0|0|0|1|1|2|0|1|1|2|0|3|2|3|1|1|3|3|6|5|6|6|11|13|17|13|16|28|24|35|46|55|68|81|109|112|137|199|213|243|301|376|442|504|565|673|747|861|1018|1143|1180|1343|1441|1519|1706|1783|1941|1947|2084|2062|2217|2234|2347|2277|2263|2267|2310|2402|2267|2298|2220|2191|2208|2133|2077|2081|2064|1957|1958|1939|1927|1862|1858|1835|1854|1898|1831|1808|1832|1770|1797|1773|1859|1851|1827|1826|1742|1767|1873|1817|1761|1790|1782|1776|1740|1692|1593|1623|1559|1570|1445|1463|1344|1323|1227|1276|1234|1131|1067|1044|966|952|899|765|721|677|651|559|557|470|390|400|381|300|270|243|202|183|158|124|108|103|89|67|57|53|52|31|43|19|22|17|15|13|9|9|7|1|3|5|2|1|3|0|2|1|4|0|0|1|0|0|2|2|0|0|2|0|0|0|0|2|0|0|0|0|0|0|0|0|0|0|0|0|0|1|0|0|0|0|0|0|1|0|0|0|0|0|0|0|1</HistCounts>
      </HistItem>
    </Histograms>
    <Metadata>
      <MDI key="STATISTICS_COVARIANCES">5.903377384878869</MDI>
      <MDI key="STATISTICS_MAXIMUM">-6.2043595314026</MDI>
      <MDI key="STATISTICS_MEAN">-19.192201719243</MDI>
      <MDI key="STATISTICS_MINIMUM">-32.475135803223</MDI>
      <MDI key="STATISTICS_SKIPFACTORX">1</MDI>
      <MDI key="STATISTICS_SKIPFACTORY">1</MDI>
      <MDI key="STATISTICS_STDDEV">2.4296866845087</MDI>
    </Metadata>
  </PAMRasterBand>
</PAMDataset>
